format4me/__init__.py
format4me-0.0.3.dist-info/LICENCE.txt
format4me-0.0.3.dist-info/METADATA
format4me-0.0.3.dist-info/WHEEL
format4me-0.0.3.dist-info/top_level.txt
format4me-0.0.3.dist-info/RECORD
