Metadata-Version: 2.1
Name: format4me
Version: 0.0.3
Summary: A library to easily format the response coming from your bard or any other ai agent .
Home-page: 
Author: Sahil Pradhan
Author-email: sahilpradhan411@gmail.com
License: MIT
Keywords: responseFormatter,chatgpt,bard
Classifier: Development Status :: 5 - Production/Stable
Classifier: Intended Audience :: Education
Classifier: Operating System :: Microsoft :: Windows :: Windows 10
Classifier: License :: OSI Approved :: MIT License
Classifier: Programming Language :: Python :: 3
License-File: LICENCE.txt
Requires-Dist: regex
